pop_create/conf.py
pop_create/scripts.py
pop_create/version.py
pop_create/pop_create/init.py
pop_create/pop_create/cicd/{{cookiecutter.root_dir}}/.brokignore
pop_create/pop_create/cicd/{{cookiecutter.root_dir}}/.coveragerc
pop_create/pop_create/cicd/{{cookiecutter.root_dir}}/.gitlab-ci.yml
pop_create/pop_create/cicd/{{cookiecutter.root_dir}}/.pre-commit-config.yaml
pop_create/pop_create/cicd/{{cookiecutter.root_dir}}/build.conf
pop_create/pop_create/cicd/{{cookiecutter.root_dir}}/noxfile.py
pop_create/pop_create/docs/init.py
pop_create/pop_create/docs/{{cookiecutter.root_dir}}/.rstcheck.cfg
pop_create/pop_create/docs/{{cookiecutter.root_dir}}/docs/conf.py
pop_create/pop_create/docs/{{cookiecutter.root_dir}}/docs/index.rst
pop_create/pop_create/docs/{{cookiecutter.root_dir}}/docs/py-modindex.rst
pop_create/pop_create/docs/{{cookiecutter.root_dir}}/docs/sitevars.rst
pop_create/pop_create/docs/{{cookiecutter.root_dir}}/docs/_includes/modindex-note.rst
pop_create/pop_create/docs/{{cookiecutter.root_dir}}/docs/_includes/reference-toc-template.rst
pop_create/pop_create/docs/{{cookiecutter.root_dir}}/docs/topics/contributing.rst
pop_create/pop_create/docs/{{cookiecutter.root_dir}}/docs/topics/license.rst
pop_create/pop_create/docs/{{cookiecutter.root_dir}}/docs/tutorial/example.rst
pop_create/pop_create/docs/{{cookiecutter.root_dir}}/docs/tutorial/index.rst
pop_create/pop_create/docs/{{cookiecutter.root_dir}}/requirements/docs.txt
pop_create/pop_create/seed/init.py
pop_create/pop_create/seed/hooks/post_gen_project.py
pop_create/pop_create/seed/hooks/pre_gen_project.py
pop_create/pop_create/seed/{{cookiecutter.root_dir}}/.gitignore
pop_create/pop_create/seed/{{cookiecutter.root_dir}}/.pyproject.toml
pop_create/pop_create/seed/{{cookiecutter.root_dir}}/CONTRIBUTING.rst
pop_create/pop_create/seed/{{cookiecutter.root_dir}}/LICENSE
pop_create/pop_create/seed/{{cookiecutter.root_dir}}/README.rst
pop_create/pop_create/seed/{{cookiecutter.root_dir}}/run.py
pop_create-8.1.2.dist-info/LICENSE
pop_create-8.1.2.dist-info/METADATA
pop_create-8.1.2.dist-info/WHEEL
pop_create-8.1.2.dist-info/entry_points.txt
pop_create-8.1.2.dist-info/top_level.txt
pop_create-8.1.2.dist-info/RECORD
